winiTranslate/__init__.py
winiTranslate/detect.py
winiTranslate/list.py
winiTranslate/translate.py
winiTranslate-0.1.dist-info/LICENSE
winiTranslate-0.1.dist-info/METADATA
winiTranslate-0.1.dist-info/WHEEL
winiTranslate-0.1.dist-info/top_level.txt
winiTranslate-0.1.dist-info/RECORD
