Metadata-Version: 2.1
Name: winiTranslate
Version: 0.1
Summary: Un module pour traduire, détecter et afficher les langues supportées par winiTranslate.
Author: soldat205
Author-email: soldat205 <winhardydev@gmail.com>
License: ### 4. `LICENSE`
Requires-Python: >=3.6
License-File: LICENSE
Requires-Dist: googletrans==4.0.0rc1
